qark/__init__.py
qark/apk_builder.py
qark/issue.py
qark/qark.py
qark/report.py
qark/utils.py
qark/xml_helpers.py
qark/decompiler/__init__.py
qark/decompiler/decompiler.py
qark/decompiler/external_decompiler.py
qark/exploit_apk/build.gradle
qark/exploit_apk/gradlew
qark/exploit_apk/gradlew.bat
qark/exploit_apk/settings.gradle
qark/exploit_apk/app/build.gradle
qark/exploit_apk/app/proguard-rules.pro
qark/exploit_apk/app/src/.DS_Store
qark/exploit_apk/app/src/main/AndroidManifest.xml
qark/exploit_apk/app/src/main/ic_launcher-web.png
qark/exploit_apk/app/src/main/ic_launcher_2-web.png
qark/exploit_apk/app/src/main/ic_launcher_droid-web.png
qark/exploit_apk/app/src/main/res/.DS_Store
qark/exploit_apk/app/src/main/res/drawable/dir_up.png
qark/exploit_apk/app/src/main/res/drawable/file_icon.png
qark/exploit_apk/app/src/main/res/drawable/folder_icon.png
qark/exploit_apk/app/src/main/res/drawable/folder_icon_light.png
qark/exploit_apk/app/src/main/res/drawable/ic_one.png
qark/exploit_apk/app/src/main/res/drawable/mipmap-hdpi/ic_launcher.png
qark/exploit_apk/app/src/main/res/drawable/mipmap-hdpi/ic_launcher_2.png
qark/exploit_apk/app/src/main/res/drawable/mipmap-mdpi/ic_launcher.png
qark/exploit_apk/app/src/main/res/drawable/mipmap-mdpi/ic_launcher_2.png
qark/exploit_apk/app/src/main/res/drawable/mipmap-xhdpi/ic_launcher.png
qark/exploit_apk/app/src/main/res/drawable/mipmap-xhdpi/ic_launcher_2.png
qark/exploit_apk/app/src/main/res/drawable/mipmap-xxhdpi/ic_launcher.png
qark/exploit_apk/app/src/main/res/drawable/mipmap-xxhdpi/ic_launcher_2.png
qark/exploit_apk/app/src/main/res/drawable/mipmap-xxxhdpi/ic_launcher.png
qark/exploit_apk/app/src/main/res/drawable/mipmap-xxxhdpi/ic_launcher_2.png
qark/exploit_apk/app/src/main/res/drawable-hdpi/drawer_shadow.9.png
qark/exploit_apk/app/src/main/res/drawable-hdpi/ic_add_black_24dp.png
qark/exploit_apk/app/src/main/res/drawable-hdpi/ic_drawer.png
qark/exploit_apk/app/src/main/res/drawable-mdpi/drawer_shadow.9.png
qark-4.0.0.dist-info/LICENSE
qark-4.0.0.dist-info/METADATA
qark-4.0.0.dist-info/WHEEL
qark-4.0.0.dist-info/entry_points.txt
qark-4.0.0.dist-info/top_level.txt
qark-4.0.0.dist-info/RECORD
