Metadata-Version: 1.1
Name: qark
Version: 4.0.0
Summary: Android static code analyzer
Home-page: https://www.github.com/linkedin/qark
Author: Tushar Dalvi & Tony Trummer
Author-email: tushardalvi@gmail.com, tonytrummer@hotmail.com
License: Apache 2.0
Keywords: android security qark exploit
Platform: UNKNOWN
Classifier: Development Status :: 4 - Beta
Classifier: Environment :: Console
Classifier: License :: OSI Approved :: Apache Software License
Classifier: Operating System :: MacOS
Classifier: Operating System :: Microsoft :: Windows
Classifier: Operating System :: Unix
Classifier: Programming Language :: Python :: 2.7
Classifier: Programming Language :: Python :: 3.6
